dlpdb/__init__.py
dlpdb/closest_line_points.py
dlpdb/coords2angles.py
dlpdb/coords2dihedrals.py
dlpdb/coords2distances.py
dlpdb/coords2helixAngleOmega.py
dlpdb/coords2projected_dihedrals.py
dlpdb/dlpdbfile.py
dlpdb/dlpisces.py
dlpdb/dna_interleave_residues.py
dlpdb/download_pdbs.py
dlpdb/dssp2pdb.py
dlpdb/has_dna_heavy_atoms.py
dlpdb/has_helices.py
dlpdb/has_protein_heavy_atoms.py
dlpdb/has_rna_heavy_atoms.py
dlpdb/has_secondary_str.py
dlpdb/has_sheets.py
dlpdb/has_turns.py
dlpdb/helixAngleOmega.py
dlpdb/merge_lines_periodic.py
dlpdb/pdb2coords.py
dlpdb/pdb2coords_ave.py
dlpdb/pdb2helix.py
dlpdb/pdb2sequence.py
dlpdb/pdb2sheet.py
dlpdb/pdb2turn.py
dlpdb/resid.py
dlpdb/select_chains_with_dna.py
dlpdb/select_interval.py
dlpdb/strip_secondary_str.py
dlpdb/truncate_chars.py
dlpdb/truncate_tokens.py
dlpdb/scripts/extract_angles.sh
dlpdb/scripts/extract_dihedrals.sh
dlpdb/scripts/extract_distances.sh
dlpdb/scripts/extract_helix_angles.sh
dlpdb/scripts/extract_helix_dihedrals.sh
dlpdb/scripts/extract_helix_distances.sh
dlpdb/scripts/extract_helix_projected_dihedrals.sh
dlpdb/scripts/extract_helix_resAveDistances.sh
dlpdb/scripts/extract_line_separation.sh
dlpdb/scripts/extract_projected_dihedrals.sh
dlpdb/scripts/extract_resAveDistances.sh
dlpdb/scripts/extract_sheet_angles.sh
dlpdb/scripts/extract_sheet_dihedrals.sh
dlpdb/scripts/extract_sheet_distances.sh
dlpdb/scripts/extract_sheet_projected_dihedrals.sh
dlpdb/scripts/extract_sheet_resAveDistances.sh
dlpdb/scripts/extract_turn_angles.sh
dlpdb/scripts/extract_turn_dihedrals.sh
dlpdb/scripts/extract_turn_distances.sh
dlpdb/scripts/extract_turn_projected_dihedrals.sh
dlpdb/scripts/extract_turn_resAveDistances.sh
dlpdb/scripts/move_membrane_proteins.sh
dlpdb/scripts/move_missing_dna_heavy_atoms.sh
dlpdb/scripts/move_missing_protein_heavy_atoms.sh
dlpdb/scripts/move_missing_secondary_str.sh
dlpdb/scripts/move_nmr_structures.sh
dlpdb/scripts/move_non-dna.sh
dlpdb/scripts/replace_all_secondary_str.sh
dlpdb-0.5.1.dist-info/LICENSE.md
dlpdb-0.5.1.dist-info/METADATA
dlpdb-0.5.1.dist-info/WHEEL
dlpdb-0.5.1.dist-info/entry_points.txt
dlpdb-0.5.1.dist-info/top_level.txt
dlpdb-0.5.1.dist-info/zip-safe
dlpdb-0.5.1.dist-info/RECORD
