Metadata-Version: 2.1
Name: dlpdb
Version: 0.5.1
Summary: collect statistics from the entire PDB library
Home-page: https://github.com/jewettaij/dlpdb
Author: Andrew Jewett
Author-email: jewett.aij@gmail.com
License: MIT
Download-URL: https://github.com/jewettaij/dlpdb/archive/v0.5.1.zip
Platform: UNKNOWN
Classifier: Development Status :: 4 - Beta
Classifier: License :: OSI Approved :: MIT License
Classifier: Environment :: Console
Classifier: Topic :: Scientific/Engineering :: Chemistry
Classifier: Operating System :: MacOS :: MacOS X
Classifier: Operating System :: POSIX :: Linux
Classifier: Operating System :: Microsoft :: Windows
Classifier: Intended Audience :: Science/Research
